swrunshell/__init__.py
swrunshell/shell_command.py
SWRunShell-1.2.dist-info/LICENSE
SWRunShell-1.2.dist-info/METADATA
SWRunShell-1.2.dist-info/WHEEL
SWRunShell-1.2.dist-info/top_level.txt
SWRunShell-1.2.dist-info/RECORD
