Metadata-Version: 2.1
Name: SWRunShell
Version: 1.2
Summary: 进一步封装了subprocess，Python调用shell命令
Home-page: https://github.com/shede333/SWRunShell
Author: shede333
Author-email: 333wshw@163.com
License: UNKNOWN
Keywords: sw shell command
Platform: UNKNOWN
Classifier: Development Status :: 5 - Production/Stable
Classifier: Natural Language :: Chinese (Simplified)
Classifier: License :: OSI Approved :: MIT License
Classifier: Operating System :: MacOS :: MacOS X
Classifier: Operating System :: POSIX
Classifier: Topic :: Software Development :: Libraries :: Python Modules
Classifier: Programming Language :: Python
Classifier: Programming Language :: Python :: 2.7
Classifier: Programming Language :: Python :: 3
Classifier: Programming Language :: Python :: 3.6
Classifier: Programming Language :: Python :: 3.7
Classifier: Programming Language :: Python :: 3.8
Requires-Python: >=2.7, !=3.0.*, !=3.1.*, !=3.2.*, !=3.3.*, !=3.4.*, <4
License-File: LICENSE
Requires-Dist: SWTermColor (~=1.1)
